{
  "schemaVersion": 1,
  "id": "irondimension",
  "name": "Iron Dimension",
  "description": "The revised port of the original Iron Dimension mod.",
  "version": "2.0.0",
  "environment": "*",
  "license": "GNU General Public License",
  "entrypoints":{
    "main": [
      "com.crypticmushroom.irondimension.IronDimension"
    ],
    "client": [
      "com.crypticmushroom.irondimension.IronDimensionClient"
    ]
  },
  "depends": {
    "fabricloader": ">=0.4.0",
    "fabric": "*"
  },
  "mixins": [
    "iron_dimension.mixins.json"
  ]
}
